heavyops.py
heavyops-0.3.0.dist-info/licenses/LICENSE
heavyops-0.3.0.dist-info/METADATA
heavyops-0.3.0.dist-info/WHEEL
heavyops-0.3.0.dist-info/entry_points.txt
heavyops-0.3.0.dist-info/top_level.txt
heavyops-0.3.0.dist-info/RECORD
