Metadata-Version: 2.4
Name: heavyops
Version: 0.3.0
Summary: Profile specific bytecode operations in a target script
Author-email: Harmen Stoppels <me@harmenstoppels.nl>
License-Expression: MIT
Keywords: profiling,bytecode,python
Classifier: Programming Language :: Python :: 3.12
Classifier: Intended Audience :: Developers
Classifier: Topic :: Software Development :: Debuggers
Classifier: Topic :: System :: Monitoring
Requires-Python: >=3.12
License-File: LICENSE
Dynamic: license-file
